drive_screen/__init__.py
drive_screen/alarm_api.py
drive_screen/alarm_panel.py
drive_screen/alarm_panel_callback_decorator.py
drive_screen/alarm_panel_callbacks.py
drive_screen/alarm_panel_layout.py
drive_screen/static/style.css
drive_screen/style.py
test_ding-0.0.1.dist-info/WHEEL
test_ding-0.0.1.dist-info/METADATA
test_ding-0.0.1.dist-info/RECORD
